panqec/__init__.py
panqec/__main__.py
panqec/analysis.py
panqec/bpauli.py
panqec/bsparse.py
panqec/cli.py
panqec/config.py
panqec/io.py
panqec/slurm.py
panqec/usage.py
panqec/utils.py
panqec/codes/__init__.py
panqec/codes/gui-config.json
panqec/codes/base/__init__.py
panqec/codes/base/_stabilizer_code.py
panqec/codes/color_2d/__init__.py
panqec/codes/color_2d/_color_488_code.py
panqec/codes/color_2d/_color_666_planar_code.py
panqec/codes/color_2d/_color_666_toric_code.py
panqec/codes/color_3d/__init__.py
panqec/codes/color_3d/_color_3d_code.py
panqec/codes/fractons/__init__.py
panqec/codes/fractons/_xcube_code.py
panqec/codes/repetition/__init__.py
panqec/codes/repetition/_repetition_code.py
panqec/codes/surface_2d/__init__.py
panqec/codes/surface_2d/_planar_2d_code.py
panqec/codes/surface_2d/_rotated_planar_2d_code.py
panqec/codes/surface_2d/_toric_2d_code.py
panqec/codes/surface_3d/__init__.py
panqec/codes/surface_3d/_hollow_planar_3d_code.py
panqec/codes/surface_3d/_hollow_rhombic_code.py
panqec/codes/surface_3d/_planar_3d_code.py
panqec/codes/surface_3d/_rhombic_planar_code.py
panqec/codes/surface_3d/_rhombic_toric_code.py
panqec/codes/surface_3d/_rotated_planar_3d_code.py
panqec/codes/surface_3d/_rotated_toric_3d_code.py
panqec/codes/surface_3d/_toric_3d_code.py
panqec/decoders/__init__.py
panqec/decoders/base/__init__.py
panqec/decoders/base/_base_decoder.py
panqec/decoders/belief_propagation/__init__.py
panqec/decoders/belief_propagation/_example_code.c
panqec/decoders/belief_propagation/bposd_decoder.py
panqec/decoders/belief_propagation/mbp_decoder.py
panqec/decoders/matching/__init__.py
panqec/decoders/matching/_matching_decoder.py
panqec/decoders/sweepmatch/__init__.py
panqec/decoders/sweepmatch/_rotated_sweep_decoder.py
panqec/decoders/sweepmatch/_rotated_sweep_match_decoder.py
panqec/decoders/sweepmatch/_sweep_decoder_3d.py
panqec/decoders/sweepmatch/_sweep_match_decoder.py
panqec/decoders/union_find/__init__.py
panqec/decoders/union_find/uf_decoder.py
panqec-0.1.7.dist-info/LICENSE
panqec-0.1.7.dist-info/METADATA
panqec-0.1.7.dist-info/WHEEL
panqec-0.1.7.dist-info/top_level.txt
panqec-0.1.7.dist-info/RECORD
